MEDS_DEV/__init__.py
MEDS_DEV/utils.py
MEDS_DEV/configs/__init__.py
MEDS_DEV/configs/_build_dataset.yaml
MEDS_DEV/configs/_evaluate_predictions.yaml
MEDS_DEV/configs/_extract_task.yaml
MEDS_DEV/configs/_package_result.yaml
MEDS_DEV/configs/_run_model.yaml
MEDS_DEV/configs/_validate_result.yaml
MEDS_DEV/datasets/README.md
MEDS_DEV/datasets/__init__.py
MEDS_DEV/datasets/__main__.py
MEDS_DEV/datasets/AUMCdb/README.md
MEDS_DEV/datasets/AUMCdb/predicates.yaml
MEDS_DEV/datasets/MIMIC-IV/README.md
MEDS_DEV/datasets/MIMIC-IV/__init__.py
MEDS_DEV/datasets/MIMIC-IV/dataset.yaml
MEDS_DEV/datasets/MIMIC-IV/predicates.yaml
MEDS_DEV/datasets/MIMIC-IV/refs.bib
MEDS_DEV/datasets/MIMIC-IV/requirements.txt
MEDS_DEV/evaluation/README.md
MEDS_DEV/evaluation/__init__.py
MEDS_DEV/evaluation/__main__.py
MEDS_DEV/models/__init__.py
MEDS_DEV/models/__main__.py
MEDS_DEV/models/cehrbert/README.md
MEDS_DEV/models/cehrbert/__init__.py
MEDS_DEV/models/cehrbert/_config.yaml
MEDS_DEV/models/cehrbert/cehrbert_finetune_template.yaml
MEDS_DEV/models/cehrbert/cehrbert_pretrain_template.yaml
MEDS_DEV/models/cehrbert/finetune_cehrbert.py
MEDS_DEV/models/cehrbert/generate_cehrbert_predictions.py
MEDS_DEV/models/cehrbert/model.yaml
MEDS_DEV/models/cehrbert/pretrain_cehrbert.py
MEDS_DEV/models/cehrbert/refs.bib
MEDS_DEV/models/cehrbert/requirements.txt
MEDS_DEV/models/genhpf/README.md
MEDS_DEV/models/genhpf/__init__.py
MEDS_DEV/models/genhpf/genhpf_predict.yaml
MEDS_DEV/models/genhpf/genhpf_train.yaml
MEDS_DEV/models/genhpf/model.yaml
MEDS_DEV/models/genhpf/refs.bib
MEDS_DEV/models/genhpf/requirements.txt
MEDS_DEV/models/meds_tab/README.md
MEDS_DEV/models/meds_tab/refs.bib
MEDS_DEV/models/meds_tab/tiny/README.md
MEDS_DEV/models/meds_tab/tiny/__init__.py
MEDS_DEV/models/meds_tab/tiny/model.yaml
MEDS_DEV/models/meds_tab/tiny/requirements.txt
MEDS_DEV/models/random_predictor/README.md
MEDS_DEV/models/random_predictor/__init__.py
MEDS_DEV/models/random_predictor/_config.yaml
meds_dev-0.0.14.dist-info/LICENSE
meds_dev-0.0.14.dist-info/METADATA
meds_dev-0.0.14.dist-info/WHEEL
meds_dev-0.0.14.dist-info/entry_points.txt
meds_dev-0.0.14.dist-info/top_level.txt
meds_dev-0.0.14.dist-info/RECORD
