Metadata-Version: 2.2
Name: MEDS_DEV
Version: 0.0.14
Summary: Task configuration and helper files for the MEDS-DEV Benchmark
Author: Nassim Oufattole
Author-email: "Matthew B. A. McDermott" <matthew_mcdermott@hms.harvard.edu>, Ethan Steinberg <ethanid@stanford.edu>, Shalmali Joshi <shalmali.joshi@columbia.edu>, "Teya S. Bergamaschi" <teya@mit.edu>, Aleksia Kolo <aleksiak@mit.edu>, Young Sang Choi <young.sang.choi@columbia.edu>, Chao Pang <cp3016@cumc.columbia.edu>, Kamilė Stankevičiūtė <kamile.stankeviciute@cst.cam.ac.uk>, Vincent Jeanselme <vincent.jeanselme@mrc-bsu.cam.ac.uk>, Justin Xu <justin.xu@ndm.ox.ac.uk>
Project-URL: Homepage, https://github.com/Medical-Event-Data-Standard/MEDS-DEV
Project-URL: Issues, https://github.com/Medical-Event-Data-Standard/MEDS-DEV/issues
Classifier: Programming Language :: Python :: 3
Classifier: License :: OSI Approved :: MIT License
Classifier: Operating System :: OS Independent
Requires-Python: >=3.11
License-File: LICENSE
Requires-Dist: meds==0.3.3
Requires-Dist: es-aces==0.6.1
Requires-Dist: hydra-core
Requires-Dist: meds-evaluation==0.0.3
Requires-Dist: validators
Provides-Extra: dev
Requires-Dist: pre-commit<4; extra == "dev"
Provides-Extra: tests
Requires-Dist: pytest; extra == "tests"
Requires-Dist: pytest-cov; extra == "tests"
Requires-Dist: meds_testing_helpers; extra == "tests"
